{
	"ident": 1001,
	"order": 1,
	"objtype": "kComponent",
	"componentlib": "jsPict",
	"componentctrl": "Picture Control",
	"properties": {
		"alpha": 255,
		"autoscroll": false,
		"backalpha": 0,
		"backcolor": "RGB(68,68,68)",
		"bordercolor": "kColorDefault",
		"borderradius": "0",
		"contextmenu": "",
		"cssclassname": "",
		"dataname": "iImageBin",
		"desgroup": 0,
		"designactive": true,
		"deslock": false,
		"disabledefaultcontextmenu": false,
		"disablesystemfocus": true,
		"dragmode": "kNoDragging",
		"dropmode": "kAcceptNone",
		"effect": "kJSborderNone",
		"enabled": true,
		"events": "evClick",
		"fieldstyle": "",
		"horzscroll": false,
		"iconid": 0,
		"keepaspectratio": true,
		"keepaspectratiomode": "kKARtopLeft",
		"linestyle": 1,
		"mediatype": "image/png",
		"noscale": true,
		"objlink": 0,
		"picturealign": 17,
		"preventlayoutanimation": false,
		"tile": false,
		"tooltip": "",
		"userinfo": "",
		"vertscroll": false,
		"visible": true
	},
	"layout": {
		"320": {
			"left": 0,
			"top": 0,
			"width": 320,
			"height": 400,
			"dragborder": false,
			"edgefloat": "kEFposnClient",
			"errortextpos": "kJSErrorTextPosUnder",
			"visible": true
		},
		"768": {
			"left": 0,
			"top": 0,
			"width": 768,
			"height": 500,
			"dragborder": false,
			"edgefloat": "kEFposnClient",
			"errortextpos": "kJSErrorTextPosUnder",
			"visible": true
		}
	}
}
